bout.py
bout-1.0.2.dist-info/LICENSE.md
bout-1.0.2.dist-info/METADATA
bout-1.0.2.dist-info/WHEEL
bout-1.0.2.dist-info/entry_points.txt
bout-1.0.2.dist-info/top_level.txt
bout-1.0.2.dist-info/RECORD
