Metadata-Version: 2.1
Name: bout
Version: 1.0.2
Summary: Parse and liberate data from csv based bank statements.
Home-page: https://github.com/codito/bout
Author: Arun Mahapatra
Author-email: arun@codito.in
License: MIT
Platform: UNKNOWN
Classifier: License :: OSI Approved :: MIT License
Classifier: Programming Language :: Python
Classifier: Programming Language :: Python :: 3
Classifier: Programming Language :: Python :: 3.6
Classifier: Programming Language :: Python :: Implementation :: CPython
Classifier: Programming Language :: Python :: Implementation :: PyPy
License-File: LICENSE.md
Requires-Dist: click (>=6.7)
